langchain_firebolt/__init__.py
langchain_firebolt/firebolt.py
langchain_firebolt-0.1.0.dist-info/licenses/LICENSE
langchain_firebolt-0.1.0.dist-info/METADATA
langchain_firebolt-0.1.0.dist-info/WHEEL
langchain_firebolt-0.1.0.dist-info/top_level.txt
langchain_firebolt-0.1.0.dist-info/RECORD
