Metadata-Version: 2.4
Name: langchain-firebolt
Version: 0.1.0
Summary: LangChain integration for Firebolt vector store
Home-page: https://github.com/firebolt-db/langchain-firebolt
Author: Firebolt Analytics
Author-email: Firebolt Analytics <support@firebolt.io>
License-Expression: Apache-2.0
Project-URL: Homepage, https://github.com/firebolt-db/langchain-firebolt
Project-URL: Documentation, https://github.com/firebolt-db/langchain-firebolt#readme
Project-URL: Repository, https://github.com/firebolt-db/langchain-firebolt
Project-URL: Issues, https://github.com/firebolt-db/langchain-firebolt/issues
Keywords: langchain,firebolt,vectorstore,embeddings,ai,llm
Classifier: Development Status :: 4 - Beta
Classifier: Intended Audience :: Developers
Classifier: Operating System :: OS Independent
Classifier: Programming Language :: Python :: 3
Classifier: Programming Language :: Python :: 3.8
Classifier: Programming Language :: Python :: 3.9
Classifier: Programming Language :: Python :: 3.10
Classifier: Programming Language :: Python :: 3.11
Classifier: Programming Language :: Python :: 3.12
Classifier: Topic :: Software Development :: Libraries :: Python Modules
Classifier: Topic :: Database
Classifier: Topic :: Scientific/Engineering :: Artificial Intelligence
Requires-Python: >=3.8
License-File: LICENSE
Requires-Dist: langchain-core>=1.2.5
Requires-Dist: pydantic>=2.0.0
Requires-Dist: pydantic-settings>=2.0.0
Requires-Dist: firebolt-sdk>=1.0.0
Requires-Dist: tqdm>=4.65.0
Provides-Extra: dev
Requires-Dist: pytest>=7.0.0; extra == "dev"
Requires-Dist: pytest-asyncio>=0.21.0; extra == "dev"
Requires-Dist: langchain-tests>=0.0.1; extra == "dev"
Requires-Dist: python-dotenv>=1.0.0; extra == "dev"
Dynamic: author
Dynamic: home-page
Dynamic: license-file
Dynamic: requires-python
